srindexproto-0.3.0.dist-info/METADATA
srindexproto-0.3.0.dist-info/WHEEL
srindexproto-0.3.0.dist-info/entry_points.txt
srindexproto-0.3.0.dist-info/licenses/LICENSE
srindexproto/__init__.py
srindexproto/cli.py
srindexproto-0.3.0.dist-info/RECORD
