Metadata-Version: 2.1
Name: SRIndexProto
Version: 0.3.0
Summary: Default template for PDM package
Author-Email: nunininu <sgcho0907@gmail.com>
License: MIT
Project-URL: Homepage, https://github.com/nuni-org/SRIndexProto
Project-URL: Issues, https://github.com/nuni-org/SRIndexProto/issues
Requires-Python: >=3.10
Requires-Dist: typer>=0.15.1
Requires-Dist: pandas>=2.2.3
